test_option_deps_new/__init__.py
test_option_deps_new-0.1.1.dist-info/METADATA
test_option_deps_new-0.1.1.dist-info/WHEEL
test_option_deps_new-0.1.1.dist-info/RECORD
